AlgorithmZhCn/README.md
AlgorithmZhCn/__init__.py
AlgorithmZhCn/__main__.py
AlgorithmZhCn/file.epub
AlgorithmZhCn/index.html
AlgorithmZhCn/css/__init__.py
AlgorithmZhCn/css/annotations.css
AlgorithmZhCn/css/main.css
AlgorithmZhCn/css/normalize.css
AlgorithmZhCn/css/popup.css
AlgorithmZhCn/font/__init__.py
AlgorithmZhCn/font/fontello.eot
AlgorithmZhCn/font/fontello.svg
AlgorithmZhCn/font/fontello.ttf
AlgorithmZhCn/font/fontello.woff
AlgorithmZhCn/img/__init__.py
AlgorithmZhCn/img/annotator-glyph-sprite.png
AlgorithmZhCn/img/annotator-icon-sprite.png
AlgorithmZhCn/img/apple-touch-icon.png
AlgorithmZhCn/img/cancelfullscreen.png
AlgorithmZhCn/img/close.png
AlgorithmZhCn/img/fullscreen.png
AlgorithmZhCn/img/loader.gif
AlgorithmZhCn/img/menu-icon.png
AlgorithmZhCn/img/save.png
AlgorithmZhCn/img/saved.png
AlgorithmZhCn/img/settings-s.png
AlgorithmZhCn/img/settings.png
AlgorithmZhCn/img/star.png
AlgorithmZhCn/js/__init__.py
AlgorithmZhCn/js/epub.js
AlgorithmZhCn/js/epub.min.js
AlgorithmZhCn/js/epub.min.map
AlgorithmZhCn/js/hooks.min.js
AlgorithmZhCn/js/hooks.min.map
AlgorithmZhCn/js/reader.js
AlgorithmZhCn/js/reader.js.map
AlgorithmZhCn/js/reader.min.js
AlgorithmZhCn/js/reader.min.map
AlgorithmZhCn/js/hooks/__init__.py
AlgorithmZhCn/js/hooks/extensions/__init__.py
AlgorithmZhCn/js/hooks/extensions/highlight.js
AlgorithmZhCn/js/libs/__init__.py
AlgorithmZhCn/js/libs/jquery.min.js
AlgorithmZhCn/js/libs/localforage.min.js
AlgorithmZhCn/js/libs/screenfull.js
AlgorithmZhCn/js/libs/screenfull.min.js
AlgorithmZhCn/js/libs/zip.min.js
AlgorithmZhCn/js/plugins/__init__.py
AlgorithmZhCn/js/plugins/hypothesis.js
AlgorithmZhCn/js/plugins/search.js
algorithm_zh_cn-2024.2.29.0.dist-info/METADATA
algorithm_zh_cn-2024.2.29.0.dist-info/WHEEL
algorithm_zh_cn-2024.2.29.0.dist-info/entry_points.txt
algorithm_zh_cn-2024.2.29.0.dist-info/top_level.txt
algorithm_zh_cn-2024.2.29.0.dist-info/RECORD
